pywwise/__init__.py
pywwise/aliases.py
pywwise/decorators.py
pywwise/descriptors.py
pywwise/enums.py
pywwise/metas.py
pywwise/modules.py
pywwise/primitives.py
pywwise/statics.py
pywwise/structs.py
pywwise/waql.py
pywwise/objects/__init__.py
pywwise/objects/abc.py
pywwise/objects/components/__init__.py
pywwise/objects/effects/__init__.py
pywwise/objects/effects/mastering_suite.py
pywwise/objects/effects/wwise_3d_audio_bed_mixer.py
pywwise/objects/effects/wwise_compressor.py
pywwise/objects/effects/wwise_convolution_reverb.py
pywwise/objects/effects/wwise_delay.py
pywwise/objects/effects/wwise_expander.py
pywwise/objects/effects/wwise_flanger.py
pywwise/objects/effects/wwise_gain.py
pywwise/objects/effects/wwise_guitar_distortion.py
pywwise/objects/effects/wwise_harmonizer.py
pywwise/objects/effects/wwise_matrix_reverb.py
pywwise/objects/effects/wwise_meter.py
pywwise/objects/effects/wwise_parametric_eq.py
pywwise/objects/effects/wwise_peak_limiter.py
pywwise/objects/effects/wwise_pitch_shifter.py
pywwise/objects/effects/wwise_recorder.py
pywwise/objects/effects/wwise_reflect.py
pywwise/objects/effects/wwise_roomverb.py
pywwise/objects/effects/wwise_stereo_delay.py
pywwise/objects/effects/wwise_time_stretch.py
pywwise/objects/effects/wwise_tremolo.py
pywwise/objects/sources/__init__.py
pywwise/objects/sources/impacter.py
pywwise/objects/sources/motion_source.py
pywwise/objects/sources/soundseed_air_wind.py
pywwise/objects/sources/soundseed_air_woosh.py
pywwise/objects/sources/soundseed_grain.py
pywwise/objects/sources/wwise_silence.py
pywwise/objects/sources/wwise_synth_one.py
pywwise/objects/sources/wwise_tone_generator.py
pywwise/objects/types/__init__.py
pywwise/objects/types/acoustic_texture.py
pywwise/objects/types/action.py
pywwise/objects/types/action_exception.py
pywwise/objects/types/actor_mixer.py
pywwise/objects/types/attenuation.py
pywwise/objects/types/audio_device.py
pywwise/objects/types/audio_source.py
pywwise/objects/types/aux_bus.py
pywwise-0.2.4.dist-info/licenses/LICENSE
pywwise-0.2.4.dist-info/METADATA
pywwise-0.2.4.dist-info/WHEEL
pywwise-0.2.4.dist-info/top_level.txt
pywwise-0.2.4.dist-info/RECORD
