Metadata-Version: 2.4
Name: pywwise
Version: 0.2.4
Summary: A comprehensive Wwise Authoring API wrapper - fully documented, with auto-completion in mind.
Author: Matheus Vilano
License: 
Project-URL: Author Website, https://www.matheusvilano.com/
Project-URL: Git Repository, https://github.com/matheusvilano/PyWwise.git
Keywords: audiokinetic,wwise,waapi,game,audio,sound,automation,scripting,asset,pipeline
Classifier: Development Status :: 4 - Beta
Classifier: Intended Audience :: Developers
Classifier: Intended Audience :: Education
Classifier: License :: OSI Approved :: Apache Software License
Classifier: Operating System :: OS Independent
Classifier: Programming Language :: Python :: 3
Requires-Python: >=3.11
License-File: LICENSE
Requires-Dist: simplevent~=2.2.0
Requires-Dist: waapi-client~=0.7.2
Dynamic: license-file
